overlays/__init__.py
overlays/client.py
overlays/helpers.py
overlays/main.py
overlays/manager.py
overlays-1.5.1.dist-info/METADATA
overlays-1.5.1.dist-info/WHEEL
overlays-1.5.1.dist-info/entry_points.txt
overlays-1.5.1.dist-info/licenses/LICENSE
overlays-1.5.1.dist-info/RECORD
