Metadata-Version: 2.4
Name: overlays
Version: 1.5.1
Summary: A lightweight Windows overlay manager and client library for creating click through overlay windows.
Project-URL: Homepage, https://github.com/aubex/overlays
Project-URL: Repository, https://github.com/aubex/overlays
Project-URL: Issues, https://github.com/aubex/overlays/issues
Author-email: Sergen Keskincelik <sergen.keskincelik@aubex.de>, Marius Räsener <marius.raesener@aubex.de>
License-File: LICENSE
Classifier: Development Status :: 4 - Beta
Classifier: Environment :: Win32 (MS Windows)
Classifier: Intended Audience :: Developers
Classifier: License :: OSI Approved :: Apache Software License
Classifier: Operating System :: Microsoft :: Windows
Classifier: Operating System :: Microsoft :: Windows :: Windows 10
Classifier: Operating System :: Microsoft :: Windows :: Windows 11
Classifier: Programming Language :: Python :: 3
Classifier: Programming Language :: Python :: 3.10
Classifier: Programming Language :: Python :: 3.11
Classifier: Programming Language :: Python :: 3.12
Classifier: Programming Language :: Python :: 3.13
Classifier: Topic :: Software Development :: Libraries :: Python Modules
Classifier: Topic :: Utilities
Requires-Python: >=3.10
Requires-Dist: pywin32>=310; sys_platform == 'win32'
Requires-Dist: qrcode>=8.2; sys_platform == 'win32'
